{
  "$schema": "https://raw.githubusercontent.com/microsoft/vcpkg-tool/main/docs/vcpkg.schema.json",
  "dependencies": [
    {
      "name": "directx-dxc",
      "host": true,
      "platform": "windows & !xbox"
    },
    {
      "name": "directx12-agility",
      "platform": "windows & !xbox"
    },
    {
      "name": "directx-headers",
      "platform": "windows & !xbox"
    },
    "directxmath",
    {
      "name": "gameinput",
      "platform": "windows & x64 & !xbox"
    },
    {
      "name": "xaudio2redist",
      "platform": "windows & !arm32 & !xbox"
    }
  ]
}
